{"total": {"lines":{"total":2030,"covered":1954,"skipped":0,"pct":96.25},"statements":{"total":2030,"covered":1954,"skipped":0,"pct":96.25},"functions":{"total":79,"covered":74,"skipped":0,"pct":93.67},"branches":{"total":132,"covered":111,"skipped":0,"pct":84.09},"branchesTrue":{"total":0,"covered":0,"skipped":0,"pct":"Unknown"}}
,"/home/user/Projects/Mine/HydrusAPI/hydrusapi.js": {"lines":{"total":2030,"covered":1954,"skipped":0,"pct":96.25},"functions":{"total":79,"covered":74,"skipped":0,"pct":93.67},"statements":{"total":2030,"covered":1954,"skipped":0,"pct":96.25},"branches":{"total":132,"covered":111,"skipped":0,"pct":84.09}}
}
